ssg/__init__.py
ssg/renderer.py
ssg/server.py
ssg/utils.py
ssg/vendor_patches.py
ssg/data_directory/__init__.py
ssg/data_directory/data.py
ssg/data_directory/data__test.py
ssg/templates/__init__.py
ssg/templates/jinja_renderer.py
ssg/templates/filters/__init__.py
ssg/templates/filters/assets.py
ssg/templates/filters/assets__test.py
ssg/templates/filters/data_structures.py
ssg/templates/filters/data_structures__test.py
ssg/templates/filters/images.py
ssg/templates/filters/images__test.py
ibots_static_site_generator-0.0.1.dist-info/METADATA
ibots_static_site_generator-0.0.1.dist-info/WHEEL
ibots_static_site_generator-0.0.1.dist-info/top_level.txt
ibots_static_site_generator-0.0.1.dist-info/RECORD
